{
  "id": "Bern-bern2016-tms",
  "featureId": "Bern2016",
  "type": "tms",
  "best": true,
  "name": "Stadt Bern 10cm (2016)",
  "url": "https://mapproxy.osm.ch/tiles/bern2016/EPSG900913/{zoom}/{x}/{y}.png?origin=nw",
  "min_zoom": 8,
  "max_zoom": 21,
  "license_url": "http://lists.openstreetmap.ch/pipermail/talk-ch/2016-November/003868.html",
  "country_code": "CH",
  "start_date": "2016",
  "end_date": "2016",
  "attribution": {
    "text": "Orthophoto 2016, Vermessungsamt Stadt Bern",
    "required": true
  }
}