{
  "id": "Loire_Atlantique-Orthophotos-2012",
  "featureId": "Loire_Atlantique-Orthophotos-2012",
  "type": "tms",
  "name": "Loire-Atlantique - Orthophotos 2012 - 20 cm",
  "url": "http://{switch:a,b,c,d,e,f,g,h}.tiles.cg44.makina-corpus.net/ortho-2012/{zoom}/{x}/{-y}.jpg",
  "max_zoom": 19,
  "license_url": "https://wiki.openstreetmap.org/wiki/FR:Sources_de_donn%C3%A9es_potentielles/France",
  "country_code": "FR",
  "start_date": "2012",
  "end_date": "2012",
  "attribution": {
    "url": "http://data.loire-atlantique.fr/licence",
    "text": "Département de Loire-Atlantique",
    "required": true
  }
}