{
  "id": "vicosa_al",
  "featureId": "vicosa_al",
  "type": "wms",
  "name": "Viçosa AL",
  "url": "http://geo.seplande.al.gov.br/teogc/terraogcwms.cgi?LAYERS=Vicosa&SERVICE=WMS&FORMAT=image/png&TRANSPARENT=TRUE&VERSION=1.1.0&SERVICE=WMS&REQUEST=GetMap&STYLES=&SRS={proj}&WIDTH={width}&HEIGHT={height}&BBOX={bbox}",
  "license_url": "http://www.acessoainformacao.gov.br/menu-de-apoio/entenda-a-lai",
  "country_code": "BR",
  "available_projections": ["EPSG:3857", "EPSG:4326", "EPSG:22525"],
  "attribution": {
    "url": "http://www.seplande.al.gov.br",
    "text": "Secretaria de Estado do Planejamento e Desenvolvimento Econômico"
  }
}